emults/__init__.py
emults/base/__init__.py
emults/base/consts.py
emults/base/exceptions.py
emults/base/grids.py
emults/base/interpolation.py
emults/base/medium.py
emults/base/obstacles.py
emults/base/text_parsing.py
emults/base/waves.py
emults/exact/__init__.py
emults/exact/convergence.py
emults/exact/single_scattering.py
emults/fd/__init__.py
emults/fd/algorithm.py
emults/fd/coefficients.py
emults/fd/grids.py
emults/fd/obstacles.py
emults/fd/plotting.py
emults/fd/solvers.py
emults/fd/utils.py
emults/fd/waves.py
emults-0.0.2.dist-info/METADATA
emults-0.0.2.dist-info/WHEEL
emults-0.0.2.dist-info/licenses/LICENSE
emults-0.0.2.dist-info/RECORD
