Metadata-Version: 2.4
Name: emults
Version: 0.0.2
Summary: Elastic multiple scattering solver using Karp Farfield Expansion artificial boundary conditions (MKFE-ABC).
Project-URL: Homepage, https://github.com/jordan-sheppard/elastic-multiple-scattering
Project-URL: Repository, https://github.com/jordan-sheppard/elastic-multiple-scattering
Project-URL: Issues, https://github.com/jordan-sheppard/elastic-multiple-scattering/issues
Author-email: Jordan Sheppard <jg.sheppard808@gmail.com>
License-Expression: MIT
License-File: LICENSE
Keywords: MKFE,MKFE-ABC,elastic,farfield,finite-difference,karp,multiple-scattering,scattering,solver,wave-scattering,waves
Classifier: License :: OSI Approved :: MIT License
Classifier: Operating System :: OS Independent
Classifier: Programming Language :: Python :: 3
Requires-Python: >=3.10
Requires-Dist: cloudpickle>=3.1.1
Requires-Dist: matplotlib>=3.9.2
Requires-Dist: numpy>=2.1.1
Requires-Dist: scipy>=1.14.1
Requires-Dist: tabulate>=0.9.0
